{
  "scanned_at": "2026-07-02T14:47:00.533040+00:00",
  "market_open": true,
  "usdcad_rate": 1.4185,
  "regime": {
    "classification": "bull",
    "vix": 16.23,
    "spy_5d_pct": 1.96,
    "spy_20d_pct": -0.69,
    "spy_above_200d": true,
    "spy_200d_ma": 6943.0,
    "computed_at": "2026-07-02T14:45:30.541564+00:00"
  },
  "tiles": {
    "indexes": [
      {
        "ticker": "^GSPTSE",
        "name": "TSX Composite",
        "currency": "CAD",
        "price": 34912.31,
        "change_pct": 0.16,
        "volume": 72888176
      },
      {
        "ticker": "^GSPC",
        "name": "S&P 500",
        "currency": "USD",
        "price": 7501.76,
        "change_pct": 0.25,
        "volume": 707176284
      },
      {
        "ticker": "^NDX",
        "name": "Nasdaq 100",
        "currency": "USD",
        "price": 29593.78,
        "change_pct": -0.72,
        "volume": 368585829
      }
    ],
    "stocks": [
      {
        "ticker": "NVDA",
        "name": "NVIDIA",
        "currency": "USD",
        "price": 196.78,
        "change_pct": -0.4,
        "volume": 30828914
      },
      {
        "ticker": "AAPL",
        "name": "Apple",
        "currency": "USD",
        "price": 306.67,
        "change_pct": 4.17,
        "volume": 18973090
      },
      {
        "ticker": "MSFT",
        "name": "Microsoft",
        "currency": "USD",
        "price": 388.94,
        "change_pct": 1.21,
        "volume": 9414544
      },
      {
        "ticker": "GOOGL",
        "name": "Alphabet",
        "currency": "USD",
        "price": 362.15,
        "change_pct": 0.26,
        "volume": 5747648
      },
      {
        "ticker": "TSLA",
        "name": "Tesla",
        "currency": "USD",
        "price": 398.08,
        "change_pct": -6.4,
        "volume": 26064957
      },
      {
        "ticker": "AMD",
        "name": "AMD",
        "currency": "USD",
        "price": 519.7,
        "change_pct": -3.92,
        "volume": 7410180
      },
      {
        "ticker": "SHOP.TO",
        "name": "Shopify",
        "currency": "CAD",
        "price": 170.03,
        "change_pct": 4.79,
        "volume": 645622
      },
      {
        "ticker": "RY.TO",
        "name": "Royal Bank of Canada",
        "currency": "CAD",
        "price": 290.23,
        "change_pct": -1.17,
        "volume": 941637
      }
    ]
  },
  "active_signals": [
    {
      "signal_type": "momentum",
      "ticker": "PANW",
      "price": 352.12,
      "pct_5d": 20.14,
      "pct_above_200d": 82.52,
      "today_pct": 0.32,
      "direction": "bullish"
    },
    {
      "signal_type": "new_high",
      "ticker": "PANW",
      "price": 352.12,
      "high_52w": 300.48,
      "pct_from_high": 17.19,
      "volume_ratio": 0.85,
      "direction": "bullish"
    },
    {
      "signal_type": "momentum",
      "ticker": "SNOW",
      "price": 258.48,
      "pct_5d": 13.84,
      "pct_above_200d": 26.15,
      "today_pct": 0.74,
      "direction": "bullish"
    },
    {
      "signal_type": "momentum",
      "ticker": "DDOG",
      "price": 260.76,
      "pct_5d": 18.02,
      "pct_above_200d": 76.09,
      "today_pct": -0.38,
      "direction": "bullish"
    },
    {
      "signal_type": "momentum",
      "ticker": "NET",
      "price": 242.54,
      "pct_5d": 7.01,
      "pct_above_200d": 17.36,
      "today_pct": 0.22,
      "direction": "bullish"
    },
    {
      "signal_type": "momentum",
      "ticker": "MDB",
      "price": 355.0,
      "pct_5d": 20.71,
      "pct_above_200d": 7.59,
      "today_pct": -0.97,
      "direction": "bullish"
    },
    {
      "signal_type": "new_high",
      "ticker": "ASML",
      "price": 1809.11,
      "high_52w": 1786.99,
      "pct_from_high": 1.24,
      "volume_ratio": 2.24,
      "direction": "bullish"
    },
    {
      "signal_type": "momentum",
      "ticker": "TSM",
      "price": 448.19,
      "pct_5d": 3.03,
      "pct_above_200d": 36.92,
      "today_pct": -0.52,
      "direction": "bullish"
    },
    {
      "signal_type": "new_high",
      "ticker": "TSM",
      "price": 447.94,
      "high_52w": 446.69,
      "pct_from_high": 0.28,
      "volume_ratio": 1.63,
      "direction": "bullish"
    },
    {
      "signal_type": "new_high",
      "ticker": "BAC",
      "price": 58.36,
      "high_52w": 56.63,
      "pct_from_high": 3.04,
      "volume_ratio": 0.89,
      "direction": "bullish"
    },
    {
      "signal_type": "momentum",
      "ticker": "V",
      "price": 356.3,
      "pct_5d": 7.8,
      "pct_above_200d": 8.39,
      "today_pct": 1.08,
      "direction": "bullish"
    },
    {
      "signal_type": "momentum",
      "ticker": "SCHW",
      "price": 96.3,
      "pct_5d": 7.67,
      "pct_above_200d": 2.08,
      "today_pct": -0.45,
      "direction": "bullish"
    },
    {
      "signal_type": "momentum",
      "ticker": "JNJ",
      "price": 260.09,
      "pct_5d": 6.21,
      "pct_above_200d": 23.0,
      "today_pct": 1.69,
      "direction": "bullish"
    },
    {
      "signal_type": "new_high",
      "ticker": "LLY",
      "price": 1230.58,
      "high_52w": 1160.8,
      "pct_from_high": 6.01,
      "volume_ratio": 1.05,
      "direction": "bullish"
    },
    {
      "signal_type": "new_high",
      "ticker": "CAT",
      "price": 980.84,
      "high_52w": 940.48,
      "pct_from_high": 4.29,
      "volume_ratio": 1.48,
      "direction": "bullish"
    },
    {
      "signal_type": "new_high",
      "ticker": "RY.TO",
      "price": 289.94,
      "high_52w": 274.74,
      "pct_from_high": 5.53,
      "volume_ratio": 1.29,
      "direction": "bullish"
    },
    {
      "signal_type": "new_high",
      "ticker": "TD.TO",
      "price": 169.97,
      "high_52w": 159.89,
      "pct_from_high": 6.3,
      "volume_ratio": 0.99,
      "direction": "bullish"
    },
    {
      "signal_type": "new_high",
      "ticker": "BNS.TO",
      "price": 121.75,
      "high_52w": 113.65,
      "pct_from_high": 7.13,
      "volume_ratio": 8.35,
      "direction": "bullish"
    },
    {
      "signal_type": "new_high",
      "ticker": "BMO.TO",
      "price": 248.23,
      "high_52w": 230.91,
      "pct_from_high": 7.5,
      "volume_ratio": 0.94,
      "direction": "bullish"
    },
    {
      "signal_type": "new_high",
      "ticker": "CM.TO",
      "price": 162.15,
      "high_52w": 160.76,
      "pct_from_high": 0.86,
      "volume_ratio": 0.93,
      "direction": "bullish"
    },
    {
      "signal_type": "momentum",
      "ticker": "FM.TO",
      "price": 39.0,
      "pct_5d": 6.12,
      "pct_above_200d": 14.9,
      "today_pct": -0.05,
      "direction": "bullish"
    },
    {
      "signal_type": "momentum",
      "ticker": "TECK-B.TO",
      "price": 85.66,
      "pct_5d": 4.3,
      "pct_above_200d": 24.65,
      "today_pct": 1.42,
      "direction": "bullish"
    },
    {
      "signal_type": "momentum",
      "ticker": "CNR.TO",
      "price": 172.74,
      "pct_5d": 4.69,
      "pct_above_200d": 23.34,
      "today_pct": 1.21,
      "direction": "bullish"
    },
    {
      "signal_type": "new_high",
      "ticker": "CNR.TO",
      "price": 172.74,
      "high_52w": 168.7,
      "pct_from_high": 2.39,
      "volume_ratio": 1.14,
      "direction": "bullish"
    },
    {
      "signal_type": "momentum",
      "ticker": "CP.TO",
      "price": 125.69,
      "pct_5d": 4.3,
      "pct_above_200d": 16.62,
      "today_pct": 1.73,
      "direction": "bullish"
    },
    {
      "signal_type": "new_high",
      "ticker": "CP.TO",
      "price": 125.69,
      "high_52w": 126.24,
      "pct_from_high": -0.44,
      "volume_ratio": 1.22,
      "direction": "bullish"
    },
    {
      "signal_type": "new_high",
      "ticker": "ATD.TO",
      "price": 89.85,
      "high_52w": 85.03,
      "pct_from_high": 5.67,
      "volume_ratio": 1.31,
      "direction": "bullish"
    },
    {
      "signal_type": "new_high",
      "ticker": "XEQT.TO",
      "price": 45.18,
      "high_52w": 45.06,
      "pct_from_high": 0.27,
      "volume_ratio": 3.36,
      "direction": "bullish"
    },
    {
      "signal_type": "new_high",
      "ticker": "VEQT.TO",
      "price": 61.36,
      "high_52w": 60.92,
      "pct_from_high": 0.72,
      "volume_ratio": 2.7,
      "direction": "bullish"
    },
    {
      "signal_type": "new_high",
      "ticker": "VGRO.TO",
      "price": 47.49,
      "high_52w": 47.44,
      "pct_from_high": 0.11,
      "volume_ratio": 2.79,
      "direction": "bullish"
    },
    {
      "signal_type": "new_high",
      "ticker": "VFV.TO",
      "price": 188.57,
      "high_52w": 187.31,
      "pct_from_high": 0.67,
      "volume_ratio": 2.44,
      "direction": "bullish"
    },
    {
      "signal_type": "new_high",
      "ticker": "XUS.TO",
      "price": 65.7,
      "high_52w": 65.36,
      "pct_from_high": 0.52,
      "volume_ratio": 2.02,
      "direction": "bullish"
    },
    {
      "signal_type": "new_high",
      "ticker": "ZEB.TO",
      "price": 75.2,
      "high_52w": 70.56,
      "pct_from_high": 6.58,
      "volume_ratio": 1.7,
      "direction": "bullish"
    },
    {
      "signal_type": "new_high",
      "ticker": "IWM",
      "price": 298.97,
      "high_52w": 292.03,
      "pct_from_high": 2.38,
      "volume_ratio": 0.91,
      "direction": "bullish"
    }
  ]
}