{
  "scanned_at": "2026-06-11T19:01:57.419614+00:00",
  "market_open": true,
  "usdcad_rate": 1.3978,
  "regime": {
    "classification": "neutral",
    "vix": 19.7,
    "spy_5d_pct": -2.78,
    "spy_20d_pct": -0.95,
    "spy_above_200d": true,
    "spy_200d_ma": 6877.06,
    "computed_at": "2026-06-11T19:00:39.533032+00:00"
  },
  "tiles": {
    "indexes": [
      {
        "ticker": "^GSPTSE",
        "name": "TSX Composite",
        "currency": "CAD",
        "price": 34657.69,
        "change_pct": 1.48,
        "volume": 142661154
      },
      {
        "ticker": "^GSPC",
        "name": "S&P 500",
        "currency": "USD",
        "price": 7372.72,
        "change_pct": 1.45,
        "volume": 2139146000
      },
      {
        "ticker": "^NDX",
        "name": "Nasdaq 100",
        "currency": "USD",
        "price": 29252.82,
        "change_pct": 2.61,
        "volume": 871671214
      }
    ],
    "stocks": [
      {
        "ticker": "NVDA",
        "name": "NVIDIA",
        "currency": "USD",
        "price": 202.7,
        "change_pct": 1.14,
        "volume": 97512742
      },
      {
        "ticker": "AAPL",
        "name": "Apple",
        "currency": "USD",
        "price": 295.2,
        "change_pct": 1.24,
        "volume": 24336006
      },
      {
        "ticker": "MSFT",
        "name": "Microsoft",
        "currency": "USD",
        "price": 387.12,
        "change_pct": -2.58,
        "volume": 28957486
      },
      {
        "ticker": "GOOGL",
        "name": "Alphabet",
        "currency": "USD",
        "price": 354.7,
        "change_pct": -0.47,
        "volume": 23275334
      },
      {
        "ticker": "TSLA",
        "name": "Tesla",
        "currency": "USD",
        "price": 393.4,
        "change_pct": 3.09,
        "volume": 31739525
      },
      {
        "ticker": "AMD",
        "name": "AMD",
        "currency": "USD",
        "price": 482.07,
        "change_pct": 6.56,
        "volume": 18951285
      },
      {
        "ticker": "SHOP.TO",
        "name": "Shopify",
        "currency": "CAD",
        "price": 151.82,
        "change_pct": 0.59,
        "volume": 1025887
      },
      {
        "ticker": "RY.TO",
        "name": "Royal Bank of Canada",
        "currency": "CAD",
        "price": 277.55,
        "change_pct": 0.65,
        "volume": 1575082
      }
    ]
  },
  "active_signals": [
    {
      "signal_type": "volume_spike",
      "ticker": "ORCL",
      "multiplier": 2.67,
      "today_volume": 52040288,
      "projected_volume": 61356604,
      "avg_volume_20d": 22954430,
      "price_change_pct": 1.42,
      "price": 182.21,
      "direction": "bullish"
    },
    {
      "signal_type": "volume_spike",
      "ticker": "SMCI",
      "multiplier": 4.87,
      "today_volume": 206549051,
      "projected_volume": 243492887,
      "avg_volume_20d": 49961380,
      "price_change_pct": 5.68,
      "price": 30.89,
      "direction": "bullish"
    }
  ]
}