{
  "scanned_at": "2026-06-11T16:31:47.802144+00:00",
  "market_open": true,
  "usdcad_rate": 1.4008,
  "regime": {
    "classification": "neutral",
    "vix": 21.31,
    "spy_5d_pct": -3.85,
    "spy_20d_pct": -2.04,
    "spy_above_200d": true,
    "spy_200d_ma": 6876.66,
    "computed_at": "2026-06-11T16:30:37.191208+00:00"
  },
  "tiles": {
    "indexes": [
      {
        "ticker": "^GSPTSE",
        "name": "TSX Composite",
        "currency": "CAD",
        "price": 34421.68,
        "change_pct": 0.79,
        "volume": 79555171
      },
      {
        "ticker": "^GSPC",
        "name": "S&P 500",
        "currency": "USD",
        "price": 7292.16,
        "change_pct": 0.35,
        "volume": 1308738000
      },
      {
        "ticker": "^NDX",
        "name": "Nasdaq 100",
        "currency": "USD",
        "price": 28814.21,
        "change_pct": 1.07,
        "volume": 544178949
      }
    ],
    "stocks": [
      {
        "ticker": "NVDA",
        "name": "NVIDIA",
        "currency": "USD",
        "price": 201.44,
        "change_pct": 0.51,
        "volume": 59996775
      },
      {
        "ticker": "AAPL",
        "name": "Apple",
        "currency": "USD",
        "price": 293.04,
        "change_pct": 0.5,
        "volume": 15260358
      },
      {
        "ticker": "MSFT",
        "name": "Microsoft",
        "currency": "USD",
        "price": 387.92,
        "change_pct": -2.38,
        "volume": 16707768
      },
      {
        "ticker": "GOOGL",
        "name": "Alphabet",
        "currency": "USD",
        "price": 348.27,
        "change_pct": -2.28,
        "volume": 16685569
      },
      {
        "ticker": "TSLA",
        "name": "Tesla",
        "currency": "USD",
        "price": 385.36,
        "change_pct": 0.99,
        "volume": 20308896
      },
      {
        "ticker": "AMD",
        "name": "AMD",
        "currency": "USD",
        "price": 465.0,
        "change_pct": 2.79,
        "volume": 12555970
      },
      {
        "ticker": "SHOP.TO",
        "name": "Shopify",
        "currency": "CAD",
        "price": 149.34,
        "change_pct": -1.06,
        "volume": 623574
      },
      {
        "ticker": "RY.TO",
        "name": "Royal Bank of Canada",
        "currency": "CAD",
        "price": 276.53,
        "change_pct": 0.28,
        "volume": 1006297
      }
    ]
  },
  "active_signals": [
    {
      "signal_type": "volume_spike",
      "ticker": "SMCI",
      "multiplier": 7.06,
      "today_volume": 163577342,
      "projected_volume": 352930180,
      "avg_volume_20d": 49961380,
      "price_change_pct": 1.71,
      "price": 29.73,
      "direction": "bullish"
    }
  ]
}